flask_launchkey.py
setup.py
launchkey_flask.egg-info/PKG-INFO
launchkey_flask.egg-info/SOURCES.txt
launchkey_flask.egg-info/dependency_links.txt
launchkey_flask.egg-info/not-zip-safe
launchkey_flask.egg-info/requires.txt
launchkey_flask.egg-info/top_level.txt