Metadata-Version: 1.1
Name: launchkey-flask
Version: 0.1.0
Summary: LaunchKey authentication extension for Flask
Home-page: https://github.com/LaunchKey/launchkey-flask
Author: Brad Porter
Author-email: UNKNOWN
License: MIT
Keywords: launchkey security authentication flask
Platform: UNKNOWN
Classifier: Programming Language :: Python
Classifier: Topic :: Internet :: WWW/HTTP
Classifier: Topic :: Internet :: WWW/HTTP :: WSGI :: Application
